.DS_Store
rnaseqhs/.DS_Store
rnaseqhs/Q20_1.py
rnaseqhs/ReadMap.R
rnaseqhs/__init__.py
rnaseqhs/command_line.py
rnaseqhs/rmN.py
rnaseqhs/rnaseqhs.py
rnaseqhs/sortCover2.py
rnaseqhs/tests/__init__.py
rnaseqhs/tests/test_rnaseqhs.py
rnaseqhs/tests/test_data/in/ERR1880444_chrX_1.fastq
rnaseqhs/tests/test_data/in2/ERR1880444_chrX_1.fastq
rnaseqhs/tests/test_data/in2/ERR1880444_chrX_2.fastq
rnaseqhs-0.3.dist-info/LICENSE
rnaseqhs-0.3.dist-info/METADATA
rnaseqhs-0.3.dist-info/WHEEL
rnaseqhs-0.3.dist-info/entry_points.txt
rnaseqhs-0.3.dist-info/top_level.txt
rnaseqhs-0.3.dist-info/RECORD
