Metadata-Version: 2.1
Name: rnaseqhs
Version: 0.3
Summary: Tool for analysis of RNA-seq data.
Home-page: https://upload.pypi.org/legacy/
Author: Zhi Zhang
Author-email: zzjerryzhang@gmail.com
License: MIT
Download-URL: https://git-r3lab.uni.lu/zhi.zhang/rnaseqhs/raw/master/rnaseqhs/dist/rnaseqhs-0.2.tar.gz
Keywords: rnaseq main
Platform: UNKNOWN
Classifier: Development Status :: 3 - Alpha
Classifier: License :: OSI Approved :: MIT License
Classifier: Programming Language :: Python :: 3.6
Classifier: Topic :: Scientific/Engineering :: Bio-Informatics
